lichess/__init__.py
lichess/client.py
lichess/formats.py
lichess/py.typed
lichess/session.py
lichess/utils.py
lichess/custom/ApiStream.py
lichess/custom/BotGameStream.py
lichess/custom/__init__.py
lichess/schemas/ArenaPerf.py
lichess/schemas/ArenaPosition.py
lichess/schemas/ArenaRatingObj.py
lichess/schemas/ArenaSheet.py
lichess/schemas/ArenaStatus.py
lichess/schemas/ArenaStatusName.py
lichess/schemas/ArenaTournament.py
lichess/schemas/ArenaTournamentFull.py
lichess/schemas/ArenaTournamentPlayed.py
lichess/schemas/ArenaTournamentPlayer.py
lichess/schemas/ArenaTournaments.py
lichess/schemas/BroadcastByUser.py
lichess/schemas/BroadcastCustomPoints.py
lichess/schemas/BroadcastCustomPointsPerColor.py
lichess/schemas/BroadcastCustomScoring.py
lichess/schemas/BroadcastForm.py
lichess/schemas/BroadcastGameEntry.py
lichess/schemas/BroadcastGroup.py
lichess/schemas/BroadcastGroupTour.py
lichess/schemas/BroadcastMyRound.py
lichess/schemas/BroadcastPlayerWithFed.py
lichess/schemas/BroadcastRoundInfo.py
lichess/schemas/BroadcastRoundStudyInfo.py
lichess/schemas/BroadcastTiebreakExtendedCode.py
lichess/schemas/BroadcastTop.py
lichess/schemas/BroadcastTour.py
lichess/schemas/BroadcastWithLastRound.py
lichess/schemas/BulkPairing.py
lichess/schemas/ChallengeCanceledEvent.py
lichess/schemas/ChallengeDeclinedEvent.py
lichess/schemas/ChallengeDeclinedJson.py
lichess/schemas/ChallengeEvent.py
lichess/schemas/ChallengeJson.py
lichess/schemas/ChallengeOpenJson.py
lichess/schemas/ChallengeStatus.py
lichess/schemas/ChallengeUser.py
lichess/schemas/ChatLineEvent.py
lichess/schemas/Clock.py
lichess/schemas/CloudEval.py
lichess/schemas/Count.py
lichess/schemas/Crosstable.py
lichess/schemas/Error.py
lichess/schemas/ExternalEngine.py
lichess/schemas/FIDEPlayer.py
lichess/schemas/Flair.py
lichess/schemas/GameChat.py
lichess/schemas/GameColor.py
lichess/schemas/GameCompat.py
lichess/schemas/GameEventInfo.py
lichess/schemas/GameEventOpponent.py
lichess/schemas/GameEventPlayer.py
lichess_api-0.5.0.dist-info/METADATA
lichess_api-0.5.0.dist-info/WHEEL
lichess_api-0.5.0.dist-info/licenses/LICENSE
lichess_api-0.5.0.dist-info/RECORD
